LICENSE.txt
MANIFEST.in
README.rst
setup.cfg
setup.py
Sijax.egg-info/PKG-INFO
Sijax.egg-info/SOURCES.txt
Sijax.egg-info/dependency_links.txt
Sijax.egg-info/not-zip-safe
Sijax.egg-info/top_level.txt
docs/Makefile
docs/api.rst
docs/comet.rst
docs/conf.py
docs/faq.rst
docs/how_to_setup.rst
docs/index.rst
docs/intro.rst
docs/make.bat
docs/upload.rst
docs/usage.rst
sijax/__init__.py
sijax/core.py
sijax/exception.py
sijax/helper.py
sijax/js/json2.js
sijax/js/sijax.js
sijax/plugin/__init__.py
sijax/plugin/comet/__init__.py
sijax/plugin/comet/js/sijax_comet.js
sijax/plugin/upload/__init__.py
sijax/plugin/upload/js/sijax_upload.js
sijax/response/__init__.py
sijax/response/base.py
sijax/response/streaming.py
tests/sijax_tests.py
tests/sijax_tests.pyc