Metadata-Version: 1.0
Name: Sijax
Version: 0.2.5
Summary: An easy to use AJAX library based on jQuery.ajax
Home-page: https://github.com/spantaleev/sijax-python
Author: Slavi Pantaleev
Author-email: s.pantaleev@gmail.com
License: BSD
Keywords: ajax,jQuery
Platform: any
Classifier: Programming Language :: Python
Classifier: Development Status :: 4 - Beta
Classifier: Environment :: Web Environment
Classifier: Intended Audience :: Developers
Classifier: License :: OSI Approved :: BSD License
Classifier: Operating System :: OS Independent
Classifier: Topic :: Internet :: WWW/HTTP :: Dynamic Content
Classifier: Topic :: Software Development :: Libraries :: Python Modules
